umetrics/__init__.py
umetrics/bleu.py
umetrics/corefmetrics.py
umetrics/macrometrics.py
umetrics/micrometrics.py
umetrics/multi_label_class_metric.py
umetrics/test_corefmetrics.py
umetrics/test_macrometrics.py
umetrics/test_micrometrics.py
u_umetrics-1.0.11.dist-info/LICENSE
u_umetrics-1.0.11.dist-info/METADATA
u_umetrics-1.0.11.dist-info/WHEEL
u_umetrics-1.0.11.dist-info/top_level.txt
u_umetrics-1.0.11.dist-info/RECORD
