Metadata-Version: 2.1
Name: u-umetrics
Version: 1.0.11
Summary: calculate precision or recall or f1 score on large-scale datasets
Home-page: https://github.com/geasyheart/u-metrics
Author: yuzhang
Author-email: geasyheart@163.com
License: MIT
Platform: UNKNOWN
License-File: LICENSE
